v2simux/__init__.py
v2simux/sim_core.py
v2simux/gui/com_no_vx.py
v2simux/gui/common.py
v2simux/gui/evtq.py
v2simux/gui/langhelper.py
v2simux/gui/cmpbox/__init__.py
v2simux/gui/cmpbox/_lang/en_US.lang
v2simux/gui/cmpbox/_lang/zh_CN.lang
v2simux/gui/convertbox/__init__.py
v2simux/gui/convertbox/_lang/en_US.lang
v2simux/gui/convertbox/_lang/zh_CN.lang
v2simux/gui/mainbox/__init__.py
v2simux/gui/mainbox/cscsveditor.py
v2simux/gui/mainbox/cseditor.py
v2simux/gui/mainbox/loadingbox.py
v2simux/gui/mainbox/plugin.py
v2simux/gui/mainbox/utils.py
v2simux/gui/mainbox/_lang/en_US.lang
v2simux/gui/mainbox/_lang/zh_CN.lang
v2simux/gui/mainbox/controls/__init__.py
v2simux/gui/mainbox/controls/lipad.py
v2simux/gui/mainbox/controls/network.py
v2simux/gui/mainbox/controls/pdfe.py
v2simux/gui/mainbox/controls/prope.py
v2simux/gui/mainbox/controls/rle.py
v2simux/gui/mainbox/controls/scrtv.py
v2simux/gui/mainbox/controls/sfe.py
v2simux/gui/mainbox/controls/sid.py
v2simux/gui/mainbox/controls/utils.py
v2simux/gui/mainbox/controls/_lang/en.lang
v2simux/gui/mainbox/controls/_lang/zh_CN.lang
v2simux/gui/parabox/__init__.py
v2simux/gui/parabox/lgb.py
v2simux/gui/parabox/pareditor.py
v2simux/gui/parabox/utils.py
v2simux/gui/parabox/_lang/en.lang
v2simux/gui/parabox/_lang/zh_CN.lang
v2simux/gui/plgbox/__init__.py
v2simux/gui/plgbox/_lang/en_US.lang
v2simux/gui/plgbox/_lang/zh_CN.lang
v2simux/gui/progbox/__init__.py
v2simux/gui/viewerbox/__init__.py
v2simux/gui/viewerbox/gridpage.py
v2simux/gui/viewerbox/optbox.py
v2simux/gui/viewerbox/plotpad.py
v2simux/gui/viewerbox/plotpage.py
v2simux/gui/viewerbox/srd.py
v2simux/gui/viewerbox/statepage.py
v2simux/gui/viewerbox/trips.py
v2simux/gui/viewerbox/_lang/en_US.lang
v2simux/gui/viewerbox/_lang/zh_CN.lang
v2simux/gui/welcomebox/__init__.py
v2simux/gui/welcomebox/v2sim.png
v2simux/gui/welcomebox/_lang/en_US.lang
v2simux/gui/welcomebox/_lang/zh_CN.lang
v2simux/locale/__init__.py
v2simux/locale/lang.py
v2simux/locale/zh_CN.py
v2simux-1.3.0rc3.dist-info/METADATA
v2simux-1.3.0rc3.dist-info/WHEEL
v2simux-1.3.0rc3.dist-info/entry_points.txt
v2simux-1.3.0rc3.dist-info/licenses/LICENSE
v2simux-1.3.0rc3.dist-info/RECORD
