Metadata-Version: 2.4
Name: v2simux
Version: 1.3.0rc3
Summary: V2Sim-UX: An Open-Source Mesoscopic V2G Simulation Platform in Urban Power and Transportation Network
Project-URL: Homepage, https://github.com/hesl-seu/v2sim
Project-URL: Documentation, https://hesl-seu.github.io/v2sim-wiki/
Project-URL: Repository, https://github.com/hesl-seu/v2sim
Project-URL: Issues, https://github.com/hesl-seu/v2sim/issues
License-Expression: BSD-3-Clause
License-File: LICENSE
Requires-Python: >=3.9
Requires-Dist: cloudpickle
Requires-Dist: dill
Requires-Dist: feasytools>=0.1.4
Requires-Dist: fpowerkit>=0.3.6.post1
Requires-Dist: matplotlib
Requires-Dist: networkx>=3.2.1
Requires-Dist: numpy
Requires-Dist: pandas>=3.0.0.dev0
Requires-Dist: pyproj
Requires-Dist: requests
Requires-Dist: scikit-learn>=1.8.dev0
Requires-Dist: sumolib
